calysto/__init__.py
calysto/display.py
calysto/graphics.py
calysto/simulation.py
calysto/zgraphics.py
calysto/ai/Numeric.py
calysto/ai/__init__.py
calysto/ai/conx.py
calysto/chart/__init__.py
calysto/chart/googlechart.py
calysto/magics/__init__.py
calysto/magics/simulation_magic.py
calysto/simulations/Bug1.py
calysto/simulations/Ladybug1.py
calysto/simulations/__init__.py
calysto/util/__init__.py
calysto/util/code2notebook.py
calysto/util/ottobib.py
calysto/util/password.py
calysto/widget/__init__.py
calysto/widget/camera.py
calysto-1.0.6.data/data/calysto/images/logo-32x32.png
calysto-1.0.6.data/data/calysto/images/logo-64x64.png
calysto-1.0.6.dist-info/METADATA
calysto-1.0.6.dist-info/RECORD
calysto-1.0.6.dist-info/WHEEL
calysto-1.0.6.dist-info/top_level.txt
