Metadata-Version: 2.1
Name: calysto
Version: 1.0.6
Summary: Libraries and Languages for Python and IPython
Home-page: https://github.com/Calysto/calysto
Author: Douglas Blank
Author-email: doug.blank@gmail.com
License: UNKNOWN
Platform: UNKNOWN
Classifier: Framework :: IPython
Classifier: License :: OSI Approved :: BSD License
Classifier: Programming Language :: Python :: 3
Classifier: Programming Language :: Python :: 2
Classifier: Programming Language :: Scheme
Requires-Dist: IPython
Requires-Dist: metakernel
Requires-Dist: svgwrite
Requires-Dist: cairosvg
Requires-Dist: ipywidgets
